MANIFEST.in
README.md
budgie.py
setup.py
tests.py
budgie.egg-info/PKG-INFO
budgie.egg-info/SOURCES.txt
budgie.egg-info/dependency_links.txt
budgie.egg-info/requires.txt
budgie.egg-info/top_level.txt