Metadata-Version: 1.1
Name: budgie
Version: 0.1
Summary: Pythonic remote commands via ssh
Home-page: http://www.python.org/puredistortion/budgie
Author: Dale Stirling and Darren Wurf
Author-email: feedback@puredistortion.com
License: UNKNOWN
Platform: UNKNOWN
Classifier: Development Status :: 4 - Beta
Classifier: Environment :: Console
Classifier: Intended Audience :: Developers
Classifier: Intended Audience :: System Administrators
Classifier: Intended Audience :: Information Technology
Classifier: Programming Language :: Python
Classifier: Programming Language :: Python :: 2
Classifier: Programming Language :: Python :: 2.6
Classifier: Programming Language :: Python :: 2.7
Classifier: Topic :: Software Development :: Build Tools
Classifier: Topic :: Software Development :: Libraries :: Python Modules
